LICENSE.txt
MANIFEST.in
README.rst
setup.py
iosxe/__init__.py
iosxe/connection.py
iosxe/core.py
iosxe/functions.py
iosxe/influxdb.py
iosxe/scripttest.py
iosxe.egg-info/PKG-INFO
iosxe.egg-info/SOURCES.txt
iosxe.egg-info/dependency_links.txt
iosxe.egg-info/not-zip-safe
iosxe.egg-info/requires.txt
iosxe.egg-info/top_level.txt