Metadata-Version: 1.1
Name: iosxe
Version: 0.3
Summary: Module for comunicate with iosxe device
Home-page: UNKNOWN
Author: Dzmitry Buynovskiy
Author-email: imperituro@mail.com
License: MIT
Keywords: iosxe CSR CSR1000V Cisco
Platform: UNKNOWN
Classifier: Development Status :: 3 - Alpha
Classifier: License :: OSI Approved :: MIT License
Classifier: Programming Language :: Python :: 2.7
Classifier: Topic :: Text Processing :: Linguistic
